PlatPingLib/__init__.py
PlatPingLib/ping.py
platping/__init__.py
platping/ping.py
PlatPingLib-1.0.dist-info/METADATA
PlatPingLib-1.0.dist-info/WHEEL
PlatPingLib-1.0.dist-info/top_level.txt
PlatPingLib-1.0.dist-info/RECORD
