Metadata-Version: 2.1
Name: PlatPingLib
Version: 1.0
Summary: A simple ping library for Python
Home-page: https://github.com/CalebFin/PlatPingLib
Author: Caleb Finigan
Author-email: cfinigan@outlook.com
Classifier: Programming Language :: Python :: 3
Classifier: License :: OSI Approved :: MIT License
